fabric_calc/__init__.py
fabric_calc/fabric_calc.py
fabric_calc-1.2.11.dist-info/LICENSE
fabric_calc-1.2.11.dist-info/WHEEL
fabric_calc-1.2.11.dist-info/METADATA
fabric_calc-1.2.11.dist-info/RECORD
